comma/__init__.py
comma/version.py
comma/application/__init__.py
comma/application/command_line.py
comma/cpp_bindings/__init__.py
comma/csv/__init__.py
comma/csv/format.py
comma/csv/options.py
comma/csv/stream.py
comma/csv/struct.py
comma/csv/time.py
comma/csv/applications/__init__.py
comma/csv/applications/csv_eval.py
comma/dictionary/__init__.py
comma/dictionary/util.py
comma/io/__init__.py
comma/io/readlines_unbuffered.py
comma/io/windows_binary.py
comma/numpy/__init__.py
comma/numpy/functions.py
comma/signal/__init__.py
comma/signal/signal.py
comma/util/__init__.py
comma/util/help_formatter.py
comma/util/warning.py
comma_py-1.2.1.dist-info/METADATA
comma_py-1.2.1.dist-info/WHEEL
comma_py-1.2.1.dist-info/entry_points.txt
comma_py-1.2.1.dist-info/top_level.txt
comma_py-1.2.1.dist-info/RECORD
