Metadata-Version: 2.1
Name: comma-py
Version: 1.2.1
Summary: csv and fixed-width binary python utilities
Home-page: https://gitlab.com/orthographic/comma
Author: vsevolod vlaskine
Author-email: vsevolod.vlaskine@gmail.com
Maintainer: vsevolod vlaskine
Maintainer-email: vsevolod.vlaskine@gmail.com
License: BSD 3-Clause
Platform: UNKNOWN
Classifier: Environment :: Console
Classifier: Intended Audience :: End Users/Desktop
Classifier: Intended Audience :: Developers
Classifier: License :: OSI Approved :: BSD License
Classifier: Operating System :: MacOS :: MacOS X
Classifier: Operating System :: Microsoft :: Windows
Classifier: Operating System :: POSIX
Classifier: Programming Language :: Python :: 3
Classifier: Topic :: Communications :: Email
Requires-Python: >=3.6
